windialog/__init__.py
windialog-1.0.2.dist-info/LICENSE.txt
windialog-1.0.2.dist-info/METADATA
windialog-1.0.2.dist-info/WHEEL
windialog-1.0.2.dist-info/top_level.txt
windialog-1.0.2.dist-info/RECORD
