Metadata-Version: 2.1
Name: windialog
Version: 1.0.2
Summary: An API to use the new Windows file & folder Dialogue Explorer
Home-page: https://github.com/MissingNo42/windialog
Author: MissingNo42
License: MIT
Download-URL: https://pypi.org/project/windialog/
Keywords: Windows,Files,Folders,Explorer,Python 3,Python 3.8
Platform: UNKNOWN
Classifier: Environment :: Win32 (MS Windows)
Classifier: Intended Audience :: Developers
Classifier: License :: OSI Approved :: MIT License
Classifier: Operating System :: Microsoft :: Windows
Classifier: Operating System :: Microsoft :: Windows :: Windows Vista
Classifier: Operating System :: Microsoft :: Windows :: Windows 7
Classifier: Operating System :: Microsoft :: Windows :: Windows 8
Classifier: Operating System :: Microsoft :: Windows :: Windows 8.1
Classifier: Operating System :: Microsoft :: Windows :: Windows 10
Classifier: Programming Language :: Python :: 3 :: Only
Classifier: Programming Language :: Python :: 3.8
Classifier: Programming Language :: Python :: 3.9
Classifier: Programming Language :: Python :: 3.10
License-File: LICENSE.txt
